structuredlogging/__init__.py
structuredlogging/requests_log.py
structuredlogging/structured_log_formatter.py
structuredlogging-1.0.5.dist-info/METADATA
structuredlogging-1.0.5.dist-info/RECORD
structuredlogging-1.0.5.dist-info/WHEEL
structuredlogging-1.0.5.dist-info/top_level.txt
