Metadata-Version: 2.1
Name: structuredlogging
Version: 1.0.5
Summary: Python Structured Log CustomFormatter
Home-page: https://github.com/AzureCATE2E/structuredlogging
Author: Azure CAT E2E
Author-email: azcate2esupport@microsoft.com
License: MIT
Download-URL: https://github.com/AzureCATE2E/structuredlogging/blob/master/dist/structuredlogging-1.0.0.tar.gz
Platform: UNKNOWN
Requires-Dist: six
Requires-Dist: requests
